Metadata-Version: 2.1
Name: odoo-addon-l10n_th_gov_purchase_agreement
Version: 16.0.1.0.0.2
Summary: Thai Localization - Government Purchase Agreement
Home-page: https://github.com/OCA/l10n-thailand
Author: Ecosoft, Odoo Community Association (OCA)
Author-email: support@odoo-community.org
License: AGPL-3
Classifier: Programming Language :: Python
Classifier: Framework :: Odoo
Classifier: Framework :: Odoo :: 16.0
Classifier: License :: OSI Approved :: GNU Affero General Public License v3
Classifier: Development Status :: 3 - Alpha
Requires-Python: >=3.10
Requires-Dist: odoo-addon-agreement-legal<16.1dev,>=16.0dev
Requires-Dist: odoo-addon-purchase-invoice-plan<16.1dev,>=16.0dev
Requires-Dist: odoo<16.1dev,>=16.0a
